[
    {
        "nid": "Purge",
        "name": "Purge",
        "desc": "",
        "icon_nid": "Light",
        "icon_index": [
            0,
            3
        ],
        "components": [
            [
                "target_enemy",
                null
            ],
            [
                "level_exp",
                null
            ],
            [
                "damage",
                10
            ],
            [
                "hit",
                75
            ],
            [
                "weapon_type",
                "Light"
            ],
            [
                "weapon_rank",
                "B"
            ],
            [
                "magic",
                null
            ],
            [
                "uses",
                5
            ],
            [
                "uses_options",
                [
                    [
                        "LoseUsesOnMiss (T/F)",
                        "F",
                        "Lose uses even on miss"
                    ]
                ]
            ],
            [
                "weight",
                20
            ],
            [
                "crit",
                5
            ],
            [
                "wexp",
                3
            ],
            [
                "value",
                3000
            ],
            [
                "min_range",
                3
            ],
            [
                "max_range",
                10
            ],
            [
                "siege_weapon",
                null
            ],
            [
                "map_hit_add_blend",
                [
                    255,
                    255,
                    0
                ]
            ]
        ]
    }
]