[
    {
        "name": "CactiDeath",
        "trigger": "unit_death",
        "level_nid": "13",
        "condition": "unit.nid == 'Cacti'",
        "commands": [],
        "only_once": false,
        "priority": 20,
        "_source": [
            "add_portrait;Cacti;Right",
            "music;Seperation",
            "speak;Cacti;No... I can't even... explore...",
            "expression;Cacti;CloseEyes",
            "remove_portrait;Cacti",
            "add_portrait;Timothy;Left",
            "speak;Timothy;Cacti... No... NO!|You fiends! Why... How could I let this happen...?",
            "music_fade_back"
        ]
    }
]